pyconductor_grpc/__init__.py
pyconductor_grpc/grpc_client.py
pyconductor_grpc/model/__init__.py
pyconductor_grpc/model/dynamicforkjointask_pb2.py
pyconductor_grpc/model/dynamicforkjointask_pb2_grpc.py
pyconductor_grpc/model/dynamicforkjointasklist_pb2.py
pyconductor_grpc/model/dynamicforkjointasklist_pb2_grpc.py
pyconductor_grpc/model/eventexecution_pb2.py
pyconductor_grpc/model/eventexecution_pb2_grpc.py
pyconductor_grpc/model/eventhandler_pb2.py
pyconductor_grpc/model/eventhandler_pb2_grpc.py
pyconductor_grpc/model/polldata_pb2.py
pyconductor_grpc/model/polldata_pb2_grpc.py
pyconductor_grpc/model/rerunworkflowrequest_pb2.py
pyconductor_grpc/model/rerunworkflowrequest_pb2_grpc.py
pyconductor_grpc/model/skiptaskrequest_pb2.py
pyconductor_grpc/model/skiptaskrequest_pb2_grpc.py
pyconductor_grpc/model/startworkflowrequest_pb2.py
pyconductor_grpc/model/startworkflowrequest_pb2_grpc.py
pyconductor_grpc/model/subworkflowparams_pb2.py
pyconductor_grpc/model/subworkflowparams_pb2_grpc.py
pyconductor_grpc/model/task_pb2.py
pyconductor_grpc/model/task_pb2_grpc.py
pyconductor_grpc/model/taskdef_pb2.py
pyconductor_grpc/model/taskdef_pb2_grpc.py
pyconductor_grpc/model/taskexeclog_pb2.py
pyconductor_grpc/model/taskexeclog_pb2_grpc.py
pyconductor_grpc/model/taskresult_pb2.py
pyconductor_grpc/model/taskresult_pb2_grpc.py
pyconductor_grpc/model/tasksummary_pb2.py
pyconductor_grpc/model/tasksummary_pb2_grpc.py
pyconductor_grpc/model/workflow_pb2.py
pyconductor_grpc/model/workflow_pb2_grpc.py
pyconductor_grpc/model/workflowdef_pb2.py
pyconductor_grpc/model/workflowdef_pb2_grpc.py
pyconductor_grpc/model/workflowsummary_pb2.py
pyconductor_grpc/model/workflowsummary_pb2_grpc.py
pyconductor_grpc/model/workflowtask_pb2.py
pyconductor_grpc/model/workflowtask_pb2_grpc.py
pyconductor_grpc/service/__init__.py
pyconductor_grpc/service/event_service_pb2.py
pyconductor_grpc/service/event_service_pb2_grpc.py
pyconductor_grpc/service/metadata_service_pb2.py
pyconductor_grpc-0.2.0.dist-info/METADATA
pyconductor_grpc-0.2.0.dist-info/WHEEL
pyconductor_grpc-0.2.0.dist-info/top_level.txt
pyconductor_grpc-0.2.0.dist-info/RECORD
