Metadata-Version: 2.1
Name: pyconductor-grpc
Version: 0.2.0
Summary: A GRPC Library for Netflix Conductor
Home-page: UNKNOWN
Author: Joseph
Author-email: joseph.solomon@invitae.com
License: UNKNOWN
Platform: UNKNOWN
Classifier: Programming Language :: Python :: 3
Classifier: License :: OSI Approved :: MIT License
Classifier: Operating System :: OS Independent
Requires-Python: >=3.6
Requires-Dist: grpcio
Requires-Dist: protobuf
Requires-Dist: typing-extensions
